LyPythonToolbox/Util_configdict.py
LyPythonToolbox/__init__.py
LyPythonToolbox/print_tricks.py
LyPythonToolbox-0.1.4.dist-info/LICENSE
LyPythonToolbox-0.1.4.dist-info/METADATA
LyPythonToolbox-0.1.4.dist-info/WHEEL
LyPythonToolbox-0.1.4.dist-info/top_level.txt
LyPythonToolbox-0.1.4.dist-info/RECORD
