Metadata-Version: 2.1
Name: LyPythonToolbox
Version: 0.1.4
Summary: Ly's personal python toolbox.
Home-page: https://github.com/YueLin301/LyPythonToolbox
Author: Yue Lin
Author-email: linyue3h1@gmail.com
License: UNKNOWN
Platform: UNKNOWN
Classifier: Programming Language :: Python :: 3
Classifier: License :: OSI Approved :: MIT License
Classifier: Operating System :: OS Independent
License-File: LICENSE
